xo/__init__.py
xo/__main__.py
xo/ai.py
xo/arbiter.py
xo/board.py
xo/cli.py
xo/error.py
xo/game.py
xo/token.py
xo-1.0.0.dist-info/DESCRIPTION.rst
xo-1.0.0.dist-info/METADATA
xo-1.0.0.dist-info/RECORD
xo-1.0.0.dist-info/WHEEL
xo-1.0.0.dist-info/entry_points.txt
xo-1.0.0.dist-info/metadata.json
xo-1.0.0.dist-info/top_level.txt
