Metadata-Version: 1.1
Name: xo
Version: 1.0.0
Summary: A Tic-tac-toe CLI game and library.
Home-page: https://github.com/dwayne/xo-python
Author: Dwayne Crooks
Author-email: me@dwaynecrooks.com
License: MIT
Keywords: tic-tac-toe tic tac toe noughts crosses
Platform: UNKNOWN
Classifier: Development Status :: 5 - Production/Stable
Classifier: Environment :: Console
Classifier: Intended Audience :: Developers
Classifier: License :: OSI Approved :: MIT License
Classifier: Operating System :: POSIX :: Linux
Classifier: Programming Language :: Python
Classifier: Programming Language :: Python :: 3.5
Classifier: Programming Language :: Python :: Implementation :: CPython
Classifier: Topic :: Games/Entertainment :: Board Games
